<Data><Panels><Panel><Struct name="Left_Right"><Component id="0" name="Left"><Layout Number="0" Position="[[0.5, 0.25, 0.5, 0.5]]" Uniformity="2" name="Left_Center_Single"><Entity Angle="2" Color="3" Size="1" Type="1" bbox="[0.5, 0.25, 0.5, 0.5]" mask="[10611,1,10614,2,10769,7,10926,9,11081,1,11083,12,11239,17,11395,20,11551,1,11553,22,11709,25,11863,1,11865,29,12022,32,12182,31,12343,30,12504,29,12665,27,12826,27,12987,25,13148,24,13309,22,13470,21,13631,20,13792,19,13953,17,14114,16,14275,14,14436,14,14597,12,14758,11,14919,9,15080,8,15241,7,15402,6,15563,4,15724,4,15885,2]" real_bbox="[0.5155, 0.2345, 0.2265, 0.2265]" /></Layout></Component><Component id="1" name="Right"><Layout Number="0" Position="[[0.5, 0.75, 0.5, 0.5]]" Uniformity="2" name="Right_Center_Single"><Entity Angle="4" Color="5" Size="5" Type="1" bbox="[0.5, 0.75, 0.5, 0.5]" mask="[8735,1,8896,3,8900,1,9056,7,9064,1,9216,11,9377,14,9536,17,9554,1,9697,21,9857,24,10018,28,10177,33,10338,34,10373,1,10498,40,10659,41,10819,43,10863,2,10979,49,11139,51,11191,2,11300,55,11460,56,11621,55,11780,55,11941,53,12101,52,12261,51,12422,49,12582,48,12742,47,12903,45,13063,44,13223,43,13383,42,13543,41,13704,39,13864,38,14024,37,14184,36,14345,34,14505,33,14666,31,14825,31,14986,29,15146,28,15306,27,15466,26,15627,24,15787,23,15948,21,16108,20,16269,18,16428,18,16588,17,16749,15,16909,14,17069,13,17230,11,17390,10,17551,8,17710,8,17870,7,18031,5,18191,4,18352,2]" real_bbox="[0.5287, 0.7787, 0.3944, 0.3944]" /></Layout></Component></Struct></Panel><Panel><Struct name="Left_Right"><Component id="0" name="Left"><Layout Number="0" Position="[[0.5, 0.25, 0.5, 0.5]]" Uniformity="2" name="Left_Center_Single"><Entity Angle="2" Color="5" Size="3" Type="1" bbox="[0.5, 0.25, 0.5, 0.5]" mask="[9660,2,9816,6,9972,1,9974,7,10129,12,10286,15,10441,2,10444,17,10599,21,10753,1,10755,25,10909,1,10911,28,11067,33,11223,1,11225,34,11379,1,11381,38,11536,43,11695,43,11854,44,12015,43,12176,41,12337,40,12498,38,12659,38,12820,37,12981,35,13142,34,13303,32,13464,31,13625,30,13786,29,13947,27,14108,27,14269,25,14430,24,14591,22,14752,22,14913,20,15074,19,15235,17,15396,16,15557,14,15718,14,15879,12,16040,11,16201,9,16362,9,16523,7,16684,6,16845,5,17006,3,17167,1]" real_bbox="[0.5221, 0.2279, 0.3104, 0.3104]" /></Layout></Component><Component id="1" name="Right"><Layout Number="0" Position="[[0.5, 0.75, 0.5, 0.5]]" Uniformity="2" name="Right_Center_Single"><Entity Angle="4" Color="6" Size="5" Type="1" bbox="[0.5, 0.75, 0.5, 0.5]" mask="[8735,1,8896,3,8900,1,9056,7,9064,1,9216,11,9377,14,9536,17,9554,1,9697,21,9857,24,10018,28,10177,33,10338,34,10373,1,10498,40,10659,41,10819,43,10863,2,10979,49,11139,51,11191,2,11300,55,11460,56,11621,55,11780,55,11941,53,12101,52,12261,51,12422,49,12582,48,12742,47,12903,45,13063,44,13223,43,13383,42,13543,41,13704,39,13864,38,14024,37,14184,36,14345,34,14505,33,14666,31,14825,31,14986,29,15146,28,15306,27,15466,26,15627,24,15787,23,15948,21,16108,20,16269,18,16428,18,16588,17,16749,15,16909,14,17069,13,17230,11,17390,10,17551,8,17710,8,17870,7,18031,5,18191,4,18352,2]" real_bbox="[0.5287, 0.7787, 0.3944, 0.3944]" /></Layout></Component></Struct></Panel><Panel><Struct name="Left_Right"><Component id="0" name="Left"><Layout Number="0" Position="[[0.5, 0.25, 0.5, 0.5]]" Uniformity="2" name="Left_Center_Single"><Entity Angle="2" Color="7" Size="5" Type="1" bbox="[0.5, 0.25, 0.5, 0.5]" mask="[8707,1,8862,1,8864,3,9018,1,9020,7,9176,11,9332,14,9488,1,9490,17,9645,21,9802,24,9957,28,10113,33,10269,1,10271,34,10425,40,10583,41,10738,2,10741,43,10895,49,11050,2,11053,51,11208,55,11367,56,11527,55,11688,55,11849,53,12010,52,12171,51,12332,49,12493,48,12654,47,12815,45,12976,44,13137,43,13298,42,13459,41,13620,39,13781,38,13942,37,14103,36,14264,34,14425,33,14586,31,14747,31,14908,29,15069,28,15230,27,15391,26,15552,24,15713,23,15874,21,16035,20,16196,18,16357,18,16518,17,16679,15,16840,14,17001,13,17162,11,17323,10,17484,8,17645,8,17806,7,17967,5,18128,4,18289,2]" real_bbox="[0.5287, 0.2213, 0.3944, 0.3944]" /></Layout></Component><Component id="1" name="Right"><Layout Number="0" Position="[[0.5, 0.75, 0.5, 0.5]]" Uniformity="2" name="Right_Center_Single"><Entity Angle="4" Color="2" Size="5" Type="1" bbox="[0.5, 0.75, 0.5, 0.5]" mask="[8735,1,8896,3,8900,1,9056,7,9064,1,9216,11,9377,14,9536,17,9554,1,9697,21,9857,24,10018,28,10177,33,10338,34,10373,1,10498,40,10659,41,10819,43,10863,2,10979,49,11139,51,11191,2,11300,55,11460,56,11621,55,11780,55,11941,53,12101,52,12261,51,12422,49,12582,48,12742,47,12903,45,13063,44,13223,43,13383,42,13543,41,13704,39,13864,38,14024,37,14184,36,14345,34,14505,33,14666,31,14825,31,14986,29,15146,28,15306,27,15466,26,15627,24,15787,23,15948,21,16108,20,16269,18,16428,18,16588,17,16749,15,16909,14,17069,13,17230,11,17390,10,17551,8,17710,8,17870,7,18031,5,18191,4,18352,2]" real_bbox="[0.5287, 0.7787, 0.3944, 0.3944]" /></Layout></Component></Struct></Panel><Panel><Struct name="Left_Right"><Component id="0" name="Left"><Layout Number="0" Position="[[0.5, 0.25, 0.5, 0.5]]" Uniformity="2" name="Left_Center_Single"><Entity Angle="3" Color="5" Size="0" Type="1" bbox="[0.5, 0.25, 0.5, 0.5]" mask="[10121,1,10280,3,10440,3,10599,5,10758,7,10918,7,11077,9,11237,9,11396,11,11556,11,11715,13,11875,13,12034,15,12194,15,12353,17,12513,17,12672,19,12831,21,12991,21,13150,23,13310,23,13469,25,13629,25,13788,27,13948,27,14107,29,14268,27]" real_bbox="[0.475, 0.25, 0.1688, 0.1812]" /></Layout></Component><Component id="1" name="Right"><Layout Number="0" Position="[[0.5, 0.75, 0.5, 0.5]]" Uniformity="2" name="Right_Center_Single"><Entity Angle="0" Color="2" Size="4" Type="1" bbox="[0.5, 0.75, 0.5, 0.5]" mask="[7968,1,8127,3,8286,5,8445,5,8604,7,8763,8,8922,9,9081,10,9240,12,9399,13,9558,15,9717,16,9876,17,10035,18,10194,20,10353,21,10512,22,10671,23,10830,25,10989,26,11148,27,11307,29,11466,30,11625,31,11784,32,11943,34,12102,34,12261,36,12420,37,12579,39,12738,40,12897,41,13056,43,13215,44,13374,45,13533,47,13692,47,13851,49,14010,50,14171,50,14332,1,14334,47,14498,43,14660,41,14824,38,14988,34,15151,32,15315,1,15317,25,15479,24,15642,21,15805,1,15807,17,15969,15,16133,11,16295,1,16297,7,16459,6,16623,2]" real_bbox="[0.4757, 0.7257, 0.3502, 0.3502]" /></Layout></Component></Struct></Panel><Panel><Struct name="Left_Right"><Component id="0" name="Left"><Layout Number="0" Position="[[0.5, 0.25, 0.5, 0.5]]" Uniformity="2" name="Left_Center_Single"><Entity Angle="3" Color="7" Size="2" Type="1" bbox="[0.5, 0.25, 0.5, 0.5]" mask="[8841,1,9000,3,9160,3,9319,5,9478,7,9638,7,9797,9,9957,9,10116,11,10276,11,10435,13,10595,13,10754,15,10913,17,11073,17,11232,19,11392,19,11551,21,11711,21,11870,23,12030,23,12189,25,12348,27,12508,27,12667,29,12827,29,12986,31,13146,31,13305,33,13465,33,13624,35,13783,37,13943,37,14102,39,14262,39,14421,41,14581,41,14740,43,14901,41]" real_bbox="[0.4625, 0.25, 0.2437, 0.2688]" /></Layout></Component><Component id="1" name="Right"><Layout Number="0" Position="[[0.5, 0.75, 0.5, 0.5]]" Uniformity="2" name="Right_Center_Single"><Entity Angle="0" Color="5" Size="4" Type="1" bbox="[0.5, 0.75, 0.5, 0.5]" mask="[7968,1,8127,3,8286,5,8445,5,8604,7,8763,8,8922,9,9081,10,9240,12,9399,13,9558,15,9717,16,9876,17,10035,18,10194,20,10353,21,10512,22,10671,23,10830,25,10989,26,11148,27,11307,29,11466,30,11625,31,11784,32,11943,34,12102,34,12261,36,12420,37,12579,39,12738,40,12897,41,13056,43,13215,44,13374,45,13533,47,13692,47,13851,49,14010,50,14171,50,14332,1,14334,47,14498,43,14660,41,14824,38,14988,34,15151,32,15315,1,15317,25,15479,24,15642,21,15805,1,15807,17,15969,15,16133,11,16295,1,16297,7,16459,6,16623,2]" real_bbox="[0.4757, 0.7257, 0.3502, 0.3502]" /></Layout></Component></Struct></Panel><Panel><Struct name="Left_Right"><Component id="0" name="Left"><Layout Number="0" Position="[[0.5, 0.25, 0.5, 0.5]]" Uniformity="2" name="Left_Center_Single"><Entity Angle="3" Color="9" Size="4" Type="1" bbox="[0.5, 0.25, 0.5, 0.5]" mask="[7561,1,7720,3,7880,3,8039,5,8198,7,8358,7,8517,9,8677,9,8836,11,8996,11,9155,13,9315,13,9474,15,9633,17,9793,17,9952,19,10112,19,10271,21,10431,21,10590,23,10749,25,10909,25,11068,27,11228,27,11387,29,11547,29,11706,31,11866,31,12025,33,12184,35,12344,35,12503,37,12663,37,12822,39,12982,39,13141,41,13300,43,13460,43,13619,45,13779,45,13938,47,14098,47,14257,49,14417,49,14576,51,14735,53,14895,53,15054,55,15214,55,15373,57,15534,55]" real_bbox="[0.45, 0.25, 0.3188, 0.3562]" /></Layout></Component><Component id="1" name="Right"><Layout Number="0" Position="[[0.5, 0.75, 0.5, 0.5]]" Uniformity="2" name="Right_Center_Single"><Entity Angle="0" Color="6" Size="4" Type="1" bbox="[0.5, 0.75, 0.5, 0.5]" mask="[7968,1,8127,3,8286,5,8445,5,8604,7,8763,8,8922,9,9081,10,9240,12,9399,13,9558,15,9717,16,9876,17,10035,18,10194,20,10353,21,10512,22,10671,23,10830,25,10989,26,11148,27,11307,29,11466,30,11625,31,11784,32,11943,34,12102,34,12261,36,12420,37,12579,39,12738,40,12897,41,13056,43,13215,44,13374,45,13533,47,13692,47,13851,49,14010,50,14171,50,14332,1,14334,47,14498,43,14660,41,14824,38,14988,34,15151,32,15315,1,15317,25,15479,24,15642,21,15805,1,15807,17,15969,15,16133,11,16295,1,16297,7,16459,6,16623,2]" real_bbox="[0.4757, 0.7257, 0.3502, 0.3502]" /></Layout></Component></Struct></Panel><Panel><Struct name="Left_Right"><Component id="0" name="Left"><Layout Number="0" Position="[[0.5, 0.25, 0.5, 0.5]]" Uniformity="2" name="Left_Center_Single"><Entity Angle="4" Color="3" Size="1" Type="1" bbox="[0.5, 0.25, 0.5, 0.5]" mask="[10587,2,10591,1,10747,7,10908,9,11068,12,11081,1,11227,17,11388,20,11548,22,11571,1,11709,25,11869,29,11899,1,12029,32,12190,31,12350,30,12510,29,12671,27,12830,27,12991,25,13151,24,13312,22,13472,21,13632,20,13792,19,13953,17,14113,16,14274,14,14433,14,14594,12,14754,11,14915,9,15075,8,15235,7,15395,6,15556,4,15715,4,15876,2]" real_bbox="[0.5155, 0.2655, 0.2265, 0.2265]" /></Layout></Component><Component id="1" name="Right"><Layout Number="0" Position="[[0.5, 0.75, 0.5, 0.5]]" Uniformity="2" name="Right_Center_Single"><Entity Angle="1" Color="6" Size="2" Type="1" bbox="[0.5, 0.75, 0.5, 0.5]" mask="[9549,1,9708,4,9868,6,10028,8,10188,9,10348,11,10508,13,10668,15,10828,17,10988,18,11148,20,11308,22,11468,24,11628,26,11788,27,11948,29,12108,31,12268,33,12428,35,12588,36,12748,38,12908,39,13068,38,13228,36,13388,35,13548,33,13708,31,13868,29,14028,27,14188,26,14348,24,14508,22,14668,20,14828,18,14988,17,15148,15,15308,13,15468,11,15628,9,15788,8,15948,6,16108,4,16269,1]" real_bbox="[0.5, 0.7875, 0.2688, 0.2437]" /></Layout></Component></Struct></Panel><Panel><Struct name="Left_Right"><Component id="0" name="Left"><Layout Number="0" Position="[[0.5, 0.25, 0.5, 0.5]]" Uniformity="2" name="Left_Center_Single"><Entity Angle="4" Color="5" Size="3" Type="1" bbox="[0.5, 0.25, 0.5, 0.5]" mask="[9621,2,9781,6,9942,7,9950,1,10102,12,10262,15,10422,17,10440,2,10583,21,10743,25,10769,1,10904,28,10933,1,11063,33,11224,34,11259,1,11384,38,11423,1,11544,43,11705,43,11865,44,12025,43,12186,41,12346,40,12507,38,12666,38,12826,37,12987,35,13147,34,13308,32,13468,31,13628,30,13788,29,13949,27,14108,27,14269,25,14429,24,14590,22,14749,22,14910,20,15070,19,15231,17,15391,16,15552,14,15711,14,15872,12,16032,11,16193,9,16352,9,16513,7,16673,6,16833,5,16994,3,17155,1]" real_bbox="[0.5221, 0.2721, 0.3104, 0.3104]" /></Layout></Component><Component id="1" name="Right"><Layout Number="0" Position="[[0.5, 0.75, 0.5, 0.5]]" Uniformity="2" name="Right_Center_Single"><Entity Angle="1" Color="2" Size="2" Type="1" bbox="[0.5, 0.75, 0.5, 0.5]" mask="[9549,1,9708,4,9868,6,10028,8,10188,9,10348,11,10508,13,10668,15,10828,17,10988,18,11148,20,11308,22,11468,24,11628,26,11788,27,11948,29,12108,31,12268,33,12428,35,12588,36,12748,38,12908,39,13068,38,13228,36,13388,35,13548,33,13708,31,13868,29,14028,27,14188,26,14348,24,14508,22,14668,20,14828,18,14988,17,15148,15,15308,13,15468,11,15628,9,15788,8,15948,6,16108,4,16269,1]" real_bbox="[0.5, 0.7875, 0.2688, 0.2437]" /></Layout></Component></Struct></Panel><Panel><Struct name="Left_Right"><Component id="0" name="Left"><Layout Number="0" Position="[[0.5, 0.25, 0.5, 0.5]]" Uniformity="2" name="Left_Center_Single"><Entity Angle="4" Color="9" Size="5" Type="1" bbox="[0.5, 0.25, 0.5, 0.5]" mask="[8655,1,8816,3,8820,1,8976,7,8984,1,9136,11,9297,14,9456,17,9474,1,9617,21,9777,24,9938,28,10097,33,10258,34,10293,1,10418,40,10579,41,10739,43,10783,2,10899,49,11059,51,11111,2,11220,55,11380,56,11541,55,11700,55,11861,53,12021,52,12181,51,12342,49,12502,48,12662,47,12823,45,12983,44,13143,43,13303,42,13463,41,13624,39,13784,38,13944,37,14104,36,14265,34,14425,33,14586,31,14745,31,14906,29,15066,28,15226,27,15386,26,15547,24,15707,23,15868,21,16028,20,16189,18,16348,18,16508,17,16669,15,16829,14,16989,13,17150,11,17310,10,17471,8,17630,8,17790,7,17951,5,18111,4,18272,2]" real_bbox="[0.5287, 0.2787, 0.3944, 0.3944]" /></Layout></Component><Component id="1" name="Right"><Layout Number="0" Position="[[0.5, 0.75, 0.5, 0.5]]" Uniformity="2" name="Right_Center_Single"><Entity Angle="1" Color="1" Size="2" Type="1" bbox="[0.5, 0.75, 0.5, 0.5]" mask="[9549,1,9708,4,9868,6,10028,8,10188,9,10348,11,10508,13,10668,15,10828,17,10988,18,11148,20,11308,22,11468,24,11628,26,11788,27,11948,29,12108,31,12268,33,12428,35,12588,36,12748,38,12908,39,13068,38,13228,36,13388,35,13548,33,13708,31,13868,29,14028,27,14188,26,14348,24,14508,22,14668,20,14828,18,14988,17,15148,15,15308,13,15468,11,15628,9,15788,8,15948,6,16108,4,16269,1]" real_bbox="[0.5, 0.7875, 0.2688, 0.2437]" /></Layout></Component></Struct></Panel><Panel><Struct name="Left_Right"><Component id="0" name="Left"><Layout Number="0" Position="[[0.5, 0.25, 0.5, 0.5]]" Uniformity="2" name="Left_Center_Single"><Entity Angle="4" Color="9" Size="5" Type="1" bbox="[0.5, 0.25, 0.5, 0.5]" mask="[8655,1,8816,3,8820,1,8976,7,8984,1,9136,11,9297,14,9456,17,9474,1,9617,21,9777,24,9938,28,10097,33,10258,34,10293,1,10418,40,10579,41,10739,43,10783,2,10899,49,11059,51,11111,2,11220,55,11380,56,11541,55,11700,55,11861,53,12021,52,12181,51,12342,49,12502,48,12662,47,12823,45,12983,44,13143,43,13303,42,13463,41,13624,39,13784,38,13944,37,14104,36,14265,34,14425,33,14586,31,14745,31,14906,29,15066,28,15226,27,15386,26,15547,24,15707,23,15868,21,16028,20,16189,18,16348,18,16508,17,16669,15,16829,14,16989,13,17150,11,17310,10,17471,8,17630,8,17790,7,17951,5,18111,4,18272,2]" real_bbox="[0.5287, 0.2787, 0.3944, 0.3944]" /></Layout></Component><Component id="1" name="Right"><Layout Number="0" Position="[[0.5, 0.75, 0.5, 0.5]]" Uniformity="2" name="Right_Center_Single"><Entity Angle="1" Color="5" Size="2" Type="1" bbox="[0.5, 0.75, 0.5, 0.5]" mask="[9549,1,9708,4,9868,6,10028,8,10188,9,10348,11,10508,13,10668,15,10828,17,10988,18,11148,20,11308,22,11468,24,11628,26,11788,27,11948,29,12108,31,12268,33,12428,35,12588,36,12748,38,12908,39,13068,38,13228,36,13388,35,13548,33,13708,31,13868,29,14028,27,14188,26,14348,24,14508,22,14668,20,14828,18,14988,17,15148,15,15308,13,15468,11,15628,9,15788,8,15948,6,16108,4,16269,1]" real_bbox="[0.5, 0.7875, 0.2688, 0.2437]" /></Layout></Component></Struct></Panel><Panel><Struct name="Left_Right"><Component id="0" name="Left"><Layout Number="0" Position="[[0.5, 0.25, 0.5, 0.5]]" Uniformity="2" name="Left_Center_Single"><Entity Angle="4" Color="9" Size="5" Type="1" bbox="[0.5, 0.25, 0.5, 0.5]" mask="[8655,1,8816,3,8820,1,8976,7,8984,1,9136,11,9297,14,9456,17,9474,1,9617,21,9777,24,9938,28,10097,33,10258,34,10293,1,10418,40,10579,41,10739,43,10783,2,10899,49,11059,51,11111,2,11220,55,11380,56,11541,55,11700,55,11861,53,12021,52,12181,51,12342,49,12502,48,12662,47,12823,45,12983,44,13143,43,13303,42,13463,41,13624,39,13784,38,13944,37,14104,36,14265,34,14425,33,14586,31,14745,31,14906,29,15066,28,15226,27,15386,26,15547,24,15707,23,15868,21,16028,20,16189,18,16348,18,16508,17,16669,15,16829,14,16989,13,17150,11,17310,10,17471,8,17630,8,17790,7,17951,5,18111,4,18272,2]" real_bbox="[0.5287, 0.2787, 0.3944, 0.3944]" /></Layout></Component><Component id="1" name="Right"><Layout Number="0" Position="[[0.5, 0.75, 0.5, 0.5]]" Uniformity="2" name="Right_Center_Single"><Entity Angle="1" Color="1" Size="1" Type="1" bbox="[0.5, 0.75, 0.5, 0.5]" mask="[10031,1,10190,4,10350,6,10510,7,10670,9,10830,11,10990,13,11150,15,11310,16,11470,18,11630,20,11790,22,11950,23,12110,25,12270,27,12430,29,12590,30,12750,32,12910,33,13070,32,13230,30,13390,29,13550,27,13710,25,13870,23,14030,22,14190,20,14350,18,14510,16,14670,15,14830,13,14990,11,15150,9,15310,7,15470,6,15630,4,15791,1]" real_bbox="[0.5, 0.7812, 0.2312, 0.2062]" /></Layout></Component></Struct></Panel><Panel><Struct name="Left_Right"><Component id="0" name="Left"><Layout Number="0" Position="[[0.5, 0.25, 0.5, 0.5]]" Uniformity="2" name="Left_Center_Single"><Entity Angle="4" Color="7" Size="5" Type="1" bbox="[0.5, 0.25, 0.5, 0.5]" mask="[8655,1,8816,3,8820,1,8976,7,8984,1,9136,11,9297,14,9456,17,9474,1,9617,21,9777,24,9938,28,10097,33,10258,34,10293,1,10418,40,10579,41,10739,43,10783,2,10899,49,11059,51,11111,2,11220,55,11380,56,11541,55,11700,55,11861,53,12021,52,12181,51,12342,49,12502,48,12662,47,12823,45,12983,44,13143,43,13303,42,13463,41,13624,39,13784,38,13944,37,14104,36,14265,34,14425,33,14586,31,14745,31,14906,29,15066,28,15226,27,15386,26,15547,24,15707,23,15868,21,16028,20,16189,18,16348,18,16508,17,16669,15,16829,14,16989,13,17150,11,17310,10,17471,8,17630,8,17790,7,17951,5,18111,4,18272,2]" real_bbox="[0.5287, 0.2787, 0.3944, 0.3944]" /></Layout></Component><Component id="1" name="Right"><Layout Number="0" Position="[[0.5, 0.75, 0.5, 0.5]]" Uniformity="2" name="Right_Center_Single"><Entity Angle="1" Color="5" Size="2" Type="1" bbox="[0.5, 0.75, 0.5, 0.5]" mask="[9549,1,9708,4,9868,6,10028,8,10188,9,10348,11,10508,13,10668,15,10828,17,10988,18,11148,20,11308,22,11468,24,11628,26,11788,27,11948,29,12108,31,12268,33,12428,35,12588,36,12748,38,12908,39,13068,38,13228,36,13388,35,13548,33,13708,31,13868,29,14028,27,14188,26,14348,24,14508,22,14668,20,14828,18,14988,17,15148,15,15308,13,15468,11,15628,9,15788,8,15948,6,16108,4,16269,1]" real_bbox="[0.5, 0.7875, 0.2688, 0.2437]" /></Layout></Component></Struct></Panel><Panel><Struct name="Left_Right"><Component id="0" name="Left"><Layout Number="0" Position="[[0.5, 0.25, 0.5, 0.5]]" Uniformity="2" name="Left_Center_Single"><Entity Angle="4" Color="7" Size="5" Type="1" bbox="[0.5, 0.25, 0.5, 0.5]" mask="[8655,1,8816,3,8820,1,8976,7,8984,1,9136,11,9297,14,9456,17,9474,1,9617,21,9777,24,9938,28,10097,33,10258,34,10293,1,10418,40,10579,41,10739,43,10783,2,10899,49,11059,51,11111,2,11220,55,11380,56,11541,55,11700,55,11861,53,12021,52,12181,51,12342,49,12502,48,12662,47,12823,45,12983,44,13143,43,13303,42,13463,41,13624,39,13784,38,13944,37,14104,36,14265,34,14425,33,14586,31,14745,31,14906,29,15066,28,15226,27,15386,26,15547,24,15707,23,15868,21,16028,20,16189,18,16348,18,16508,17,16669,15,16829,14,16989,13,17150,11,17310,10,17471,8,17630,8,17790,7,17951,5,18111,4,18272,2]" real_bbox="[0.5287, 0.2787, 0.3944, 0.3944]" /></Layout></Component><Component id="1" name="Right"><Layout Number="0" Position="[[0.5, 0.75, 0.5, 0.5]]" Uniformity="2" name="Right_Center_Single"><Entity Angle="1" Color="5" Size="1" Type="1" bbox="[0.5, 0.75, 0.5, 0.5]" mask="[10031,1,10190,4,10350,6,10510,7,10670,9,10830,11,10990,13,11150,15,11310,16,11470,18,11630,20,11790,22,11950,23,12110,25,12270,27,12430,29,12590,30,12750,32,12910,33,13070,32,13230,30,13390,29,13550,27,13710,25,13870,23,14030,22,14190,20,14350,18,14510,16,14670,15,14830,13,14990,11,15150,9,15310,7,15470,6,15630,4,15791,1]" real_bbox="[0.5, 0.7812, 0.2312, 0.2062]" /></Layout></Component></Struct></Panel><Panel><Struct name="Left_Right"><Component id="0" name="Left"><Layout Number="0" Position="[[0.5, 0.25, 0.5, 0.5]]" Uniformity="2" name="Left_Center_Single"><Entity Angle="4" Color="7" Size="5" Type="1" bbox="[0.5, 0.25, 0.5, 0.5]" mask="[8655,1,8816,3,8820,1,8976,7,8984,1,9136,11,9297,14,9456,17,9474,1,9617,21,9777,24,9938,28,10097,33,10258,34,10293,1,10418,40,10579,41,10739,43,10783,2,10899,49,11059,51,11111,2,11220,55,11380,56,11541,55,11700,55,11861,53,12021,52,12181,51,12342,49,12502,48,12662,47,12823,45,12983,44,13143,43,13303,42,13463,41,13624,39,13784,38,13944,37,14104,36,14265,34,14425,33,14586,31,14745,31,14906,29,15066,28,15226,27,15386,26,15547,24,15707,23,15868,21,16028,20,16189,18,16348,18,16508,17,16669,15,16829,14,16989,13,17150,11,17310,10,17471,8,17630,8,17790,7,17951,5,18111,4,18272,2]" real_bbox="[0.5287, 0.2787, 0.3944, 0.3944]" /></Layout></Component><Component id="1" name="Right"><Layout Number="0" Position="[[0.5, 0.75, 0.5, 0.5]]" Uniformity="2" name="Right_Center_Single"><Entity Angle="1" Color="1" Size="2" Type="1" bbox="[0.5, 0.75, 0.5, 0.5]" mask="[9549,1,9708,4,9868,6,10028,8,10188,9,10348,11,10508,13,10668,15,10828,17,10988,18,11148,20,11308,22,11468,24,11628,26,11788,27,11948,29,12108,31,12268,33,12428,35,12588,36,12748,38,12908,39,13068,38,13228,36,13388,35,13548,33,13708,31,13868,29,14028,27,14188,26,14348,24,14508,22,14668,20,14828,18,14988,17,15148,15,15308,13,15468,11,15628,9,15788,8,15948,6,16108,4,16269,1]" real_bbox="[0.5, 0.7875, 0.2688, 0.2437]" /></Layout></Component></Struct></Panel><Panel><Struct name="Left_Right"><Component id="0" name="Left"><Layout Number="0" Position="[[0.5, 0.25, 0.5, 0.5]]" Uniformity="2" name="Left_Center_Single"><Entity Angle="4" Color="7" Size="5" Type="1" bbox="[0.5, 0.25, 0.5, 0.5]" mask="[8655,1,8816,3,8820,1,8976,7,8984,1,9136,11,9297,14,9456,17,9474,1,9617,21,9777,24,9938,28,10097,33,10258,34,10293,1,10418,40,10579,41,10739,43,10783,2,10899,49,11059,51,11111,2,11220,55,11380,56,11541,55,11700,55,11861,53,12021,52,12181,51,12342,49,12502,48,12662,47,12823,45,12983,44,13143,43,13303,42,13463,41,13624,39,13784,38,13944,37,14104,36,14265,34,14425,33,14586,31,14745,31,14906,29,15066,28,15226,27,15386,26,15547,24,15707,23,15868,21,16028,20,16189,18,16348,18,16508,17,16669,15,16829,14,16989,13,17150,11,17310,10,17471,8,17630,8,17790,7,17951,5,18111,4,18272,2]" real_bbox="[0.5287, 0.2787, 0.3944, 0.3944]" /></Layout></Component><Component id="1" name="Right"><Layout Number="0" Position="[[0.5, 0.75, 0.5, 0.5]]" Uniformity="2" name="Right_Center_Single"><Entity Angle="1" Color="1" Size="1" Type="1" bbox="[0.5, 0.75, 0.5, 0.5]" mask="[10031,1,10190,4,10350,6,10510,7,10670,9,10830,11,10990,13,11150,15,11310,16,11470,18,11630,20,11790,22,11950,23,12110,25,12270,27,12430,29,12590,30,12750,32,12910,33,13070,32,13230,30,13390,29,13550,27,13710,25,13870,23,14030,22,14190,20,14350,18,14510,16,14670,15,14830,13,14990,11,15150,9,15310,7,15470,6,15630,4,15791,1]" real_bbox="[0.5, 0.7812, 0.2312, 0.2062]" /></Layout></Component></Struct></Panel><Panel><Struct name="Left_Right"><Component id="0" name="Left"><Layout Number="0" Position="[[0.5, 0.25, 0.5, 0.5]]" Uniformity="2" name="Left_Center_Single"><Entity Angle="4" Color="9" Size="5" Type="1" bbox="[0.5, 0.25, 0.5, 0.5]" mask="[8655,1,8816,3,8820,1,8976,7,8984,1,9136,11,9297,14,9456,17,9474,1,9617,21,9777,24,9938,28,10097,33,10258,34,10293,1,10418,40,10579,41,10739,43,10783,2,10899,49,11059,51,11111,2,11220,55,11380,56,11541,55,11700,55,11861,53,12021,52,12181,51,12342,49,12502,48,12662,47,12823,45,12983,44,13143,43,13303,42,13463,41,13624,39,13784,38,13944,37,14104,36,14265,34,14425,33,14586,31,14745,31,14906,29,15066,28,15226,27,15386,26,15547,24,15707,23,15868,21,16028,20,16189,18,16348,18,16508,17,16669,15,16829,14,16989,13,17150,11,17310,10,17471,8,17630,8,17790,7,17951,5,18111,4,18272,2]" real_bbox="[0.5287, 0.2787, 0.3944, 0.3944]" /></Layout></Component><Component id="1" name="Right"><Layout Number="0" Position="[[0.5, 0.75, 0.5, 0.5]]" Uniformity="2" name="Right_Center_Single"><Entity Angle="1" Color="5" Size="1" Type="1" bbox="[0.5, 0.75, 0.5, 0.5]" mask="[10031,1,10190,4,10350,6,10510,7,10670,9,10830,11,10990,13,11150,15,11310,16,11470,18,11630,20,11790,22,11950,23,12110,25,12270,27,12430,29,12590,30,12750,32,12910,33,13070,32,13230,30,13390,29,13550,27,13710,25,13870,23,14030,22,14190,20,14350,18,14510,16,14670,15,14830,13,14990,11,15150,9,15310,7,15470,6,15630,4,15791,1]" real_bbox="[0.5, 0.7812, 0.2312, 0.2062]" /></Layout></Component></Struct></Panel></Panels><Rules><Rule_Group id="0"><Rule attr="Number/Position" name="Constant" /><Rule attr="Type" name="Constant" /><Rule attr="Size" name="Progression" /><Rule attr="Color" name="Progression" /></Rule_Group><Rule_Group id="1"><Rule attr="Number/Position" name="Constant" /><Rule attr="Type" name="Constant" /><Rule attr="Size" name="Constant" /><Rule attr="Color" name="Distribute_Three" /></Rule_Group></Rules><Modified_attributes><Candidate id="0"><Attribute component_id="0" name="Color" /><Attribute component_id="1" name="Color" /></Candidate><Candidate id="1"><Attribute component_id="0" name="Color" /></Candidate><Candidate id="2"><Attribute component_id="1" name="Size" /><Attribute component_id="0" name="Color" /><Attribute component_id="1" name="Color" /></Candidate><Candidate id="3" /><Candidate id="4"><Attribute component_id="1" name="Size" /></Candidate><Candidate id="5"><Attribute component_id="1" name="Color" /></Candidate><Candidate id="6"><Attribute component_id="1" name="Size" /><Attribute component_id="1" name="Color" /></Candidate><Candidate id="7"><Attribute component_id="1" name="Size" /><Attribute component_id="0" name="Color" /></Candidate></Modified_attributes></Data>